FunPayAPI/__init__.py
FunPayAPI/account.py
FunPayAPI/exceptions.py
FunPayAPI/runner.py
FunPayAPI/types.py
FunPayAPI/users.py
FunPayAPI/utils.py
FunPayAPI-0.0.2.dist-info/LICENSE
FunPayAPI-0.0.2.dist-info/METADATA
FunPayAPI-0.0.2.dist-info/WHEEL
FunPayAPI-0.0.2.dist-info/top_level.txt
FunPayAPI-0.0.2.dist-info/RECORD
